{
    "type": "FeatureCollection",
    "unit": "m",
    "features": [
        {
            "type": "Feature",
            "geometry": {
                "type": "GeometryCollection",
                "geometries": [
                    {
                        "type": "Point",
                        "coordinates": [
                            478482.9,
                            3670320.02
                        ]
                    },
                    {
                        "type": "LineString",
                        "coordinates": [
                            [
                                478482.9,
                                3670320.02,
                                37.46
                            ],
                            [
                                478482.9013,
                                3670320.041,
                                25.675025144
                            ],
                            [
                                478482.90522,
                                3670320.1041,
                                13.890201154
                            ],
                            [
                                478482.9293,
                                3670320.2072,
                                0.3106185693
                            ],
                            [
                                478482.9895,
                                3670320.3226,
                                -13.26875305
                            ],
                            [
                                478483.07909,
                                3670320.454,
                                -27.41285721
                            ],
                            [
                                478483.18479,
                                3670320.5951,
                                -41.55675628
                            ],
                            [
                                478483.29822,
                                3670320.7405,
                                -55.69555293
                            ],
                            [
                                478483.41106,
                                3670320.8848,
                                -69.83436563
                            ],
                            [
                                478483.52594,
                                3670321.0208,
                                -83.94324035
                            ],
                            [
                                478483.64598,
                                3670321.1421,
                                -98.05220662
                            ],
                            [
                                478483.77031,
                                3670321.2401,
                                -111.8462955
                            ],
                            [
                                478483.90353,
                                3670321.3111,
                                -125.6404663
                            ],
                            [
                                478484.03427,
                                3670321.3786,
                                -139.4346793
                            ],
                            [
                                478484.15118,
                                3670321.4659,
                                -153.2289051
                            ],
                            [
                                478484.2665,
                                3670321.5483,
                                -166.7081567
                            ],
                            [
                                478484.39751,
                                3670321.6054,
                                -180.1873957
                            ],
                            [
                                478484.5212,
                                3670321.6515,
                                -193.4067341
                            ],
                            [
                                478484.61995,
                                3670321.7025,
                                -206.6262646
                            ],
                            [
                                478484.69854,
                                3670321.7366,
                                -222.3810159
                            ],
                            [
                                478484.72871,
                                3670321.7116,
                                -238.1359516
                            ],
                            [
                                478484.74192,
                                3670321.634,
                                -251.9207156
                            ],
                            [
                                478484.77111,
                                3670321.4971,
                                -265.7049925
                            ],
                            [
                                478484.80652,
                                3670321.3255,
                                -279.4638761
                            ],
                            [
                                478484.83849,
                                3670321.1435,
                                -293.2226339
                            ],
                            [
                                478484.86342,
                                3670320.9764,
                                -307.1165991
                            ],
                            [
                                478484.8771,
                                3670320.853,
                                -321.0110379
                            ],
                            [
                                478484.87111,
                                3670320.7496,
                                -334.8306474
                            ],
                            [
                                478484.83711,
                                3670320.6415,
                                -348.6501794
                            ],
                            [
                                478484.78703,
                                3670320.5634,
                                -363.1098653
                            ],
                            [
                                478484.73729,
                                3670320.5605,
                                -377.5697631
                            ],
                            [
                                478484.6868,
                                3670320.589,
                                -391.9396455
                            ],
                            [
                                478484.63387,
                                3670320.6055,
                                -406.3095381
                            ],
                            [
                                478484.53909,
                                3670320.6323,
                                -420.7291795
                            ],
                            [
                                478484.36341,
                                3670320.6915,
                                -435.1479647
                            ],
                            [
                                478484.15489,
                                3670320.7651,
                                -449.5912699
                            ],
                            [
                                478483.96235,
                                3670320.8348,
                                -464.0348168
                            ],
                            [
                                478483.76303,
                                3670320.9062,
                                -478.4382568
                            ],
                            [
                                478483.53318,
                                3670320.9854,
                                -492.8412005
                            ],
                            [
                                478483.29663,
                                3670321.0723,
                                -507.2990016
                            ],
                            [
                                478483.07907,
                                3670321.1659,
                                -521.757059
                            ],
                            [
                                478482.87077,
                                3670321.2765,
                                -536.1501229
                            ],
                            [
                                478482.66007,
                                3670321.4152,
                                -550.5429089
                            ],
                            [
                                478482.44085,
                                3670321.5591,
                                -564.9305159
                            ],
                            [
                                478482.2068,
                                3670321.6855,
                                -579.3180535
                            ],
                            [
                                478481.95938,
                                3670321.8091,
                                -593.730397
                            ],
                            [
                                478481.70091,
                                3670321.9443,
                                -608.1424428
                            ],
                            [
                                478481.45319,
                                3670322.0805,
                                -622.5796698
                            ],
                            [
                                478481.23897,
                                3670322.2067,
                                -637.0175233
                            ],
                            [
                                478481.04854,
                                3670322.3321,
                                -651.4407189
                            ],
                            [
                                478480.87183,
                                3670322.466,
                                -665.8640129
                            ],
                            [
                                478480.69675,
                                3670322.5925,
                                -680.2473882
                            ],
                            [
                                478480.51029,
                                3670322.6964,
                                -694.6308012
                            ],
                            [
                                478480.32013,
                                3670322.7852,
                                -709.0392715
                            ],
                            [
                                478480.13461,
                                3670322.8659,
                                -723.4478498
                            ],
                            [
                                478479.95748,
                                3670322.9551,
                                -737.851481
                            ],
                            [
                                478479.7924,
                                3670323.0696,
                                -752.2550772
                            ],
                            [
                                478479.63009,
                                3670323.1964,
                                -766.6536028
                            ],
                            [
                                478479.46119,
                                3670323.3228,
                                -781.0520556
                            ],
                            [
                                478479.28193,
                                3670323.4407,
                                -795.4454544
                            ],
                            [
                                478479.08843,
                                3670323.5417,
                                -809.8387962
                            ],
                            [
                                478478.89293,
                                3670323.6373,
                                -824.227149
                            ],
                            [
                                478478.70752,
                                3670323.7387,
                                -838.6155954
                            ],
                            [
                                478478.52216,
                                3670323.8486,
                                -853.018982
                            ],
                            [
                                478478.32717,
                                3670323.9692,
                                -867.4221551
                            ],
                            [
                                478478.1379,
                                3670324.0858,
                                -881.7804311
                            ],
                            [
                                478477.96846,
                                3670324.1843,
                                -896.1390905
                            ],
                            [
                                478477.7915,
                                3670324.2833,
                                -910.5776612
                            ],
                            [
                                478477.58147,
                                3670324.4006,
                                -925.0156513
                            ],
                            [
                                478477.35057,
                                3670324.5402,
                                -939.488133
                            ],
                            [
                                478477.11211,
                                3670324.7052,
                                -953.9602231
                            ],
                            [
                                478476.87413,
                                3670324.8727,
                                -968.3472769
                            ],
                            [
                                478476.6418,
                                3670325.0216,
                                -982.7346278
                            ],
                            [
                                478476.40972,
                                3670325.1573,
                                -997.1421171
                            ],
                            [
                                478476.17309,
                                3670325.285,
                                -1011.549606
                            ],
                            [
                                478475.93821,
                                3670325.4151,
                                -1025.982106
                            ],
                            [
                                478475.71217,
                                3670325.5576,
                                -1040.41463
                            ],
                            [
                                478475.51236,
                                3670325.6963,
                                -1054.75756
                            ],
                            [
                                478475.35337,
                                3670325.8167,
                                -1069.101167
                            ],
                            [
                                478475.22678,
                                3670325.9488,
                                -1083.54
                            ],
                            [
                                478475.12599,
                                3670326.1212,
                                -1097.978612
                            ],
                            [
                                478475.00887,
                                3670326.2989,
                                -1112.327019
                            ],
                            [
                                478474.83221,
                                3670326.4496,
                                -1126.675127
                            ],
                            [
                                478474.62257,
                                3670326.5842,
                                -1141.102974
                            ],
                            [
                                478474.4088,
                                3670326.7122,
                                -1155.530821
                            ],
                            [
                                478474.19761,
                                3670326.8275,
                                -1169.948811
                            ],
                            [
                                478473.99543,
                                3670326.9246,
                                -1184.367064
                            ],
                            [
                                478473.79003,
                                3670326.9907,
                                -1198.690431
                            ],
                            [
                                478473.56664,
                                3670327.0144,
                                -1213.013662
                            ],
                            [
                                478473.28507,
                                3670327.0088,
                                -1227.435884
                            ],
                            [
                                478472.90842,
                                3670326.9867,
                                -1241.855918
                            ],
                            [
                                478472.50374,
                                3670326.9252,
                                -1256.295096
                            ],
                            [
                                478472.13924,
                                3670326.8008,
                                -1270.734941
                            ],
                            [
                                478471.78112,
                                3670326.6746,
                                -1285.104909
                            ],
                            [
                                478471.39223,
                                3670326.606,
                                -1299.474467
                            ],
                            [
                                478470.97978,
                                3670326.5627,
                                -1313.94352
                            ],
                            [
                                478470.5566,
                                3670326.5132,
                                -1328.412243
                            ],
                            [
                                478470.13499,
                                3670326.4514,
                                -1342.85095
                            ],
                            [
                                478469.72549,
                                3670326.3711,
                                -1357.289915
                            ],
                            [
                                478469.32772,
                                3670326.3198,
                                -1371.709317
                            ],
                            [
                                478468.9402,
                                3670326.3446,
                                -1386.129069
                            ],
                            [
                                478468.55362,
                                3670326.3945,
                                -1400.448758
                            ],
                            [
                                478468.15334,
                                3670326.4195,
                                -1414.768136
                            ],
                            [
                                478467.75457,
                                3670326.4286,
                                -1429.167606
                            ],
                            [
                                478467.37706,
                                3670326.4312,
                                -1443.567653
                            ],
                            [
                                478467.18722,
                                3670326.4269,
                                -1450.69512
                            ],
                            [
                                478466.9809,
                                3670326.4148,
                                -1457.82212
                            ],
                            [
                                478466.13233,
                                3670326.3836,
                                -1486.589572
                            ],
                            [
                                478465.31882,
                                3670326.4197,
                                -1515.358032
                            ],
                            [
                                478464.54038,
                                3670326.5231,
                                -1544.1273
                            ],
                            [
                                478463.36758,
                                3670326.6956,
                                -1587.666146
                            ],
                            [
                                478462.15226,
                                3670326.7983,
                                -1631.204047
                            ],
                            [
                                478460.94766,
                                3670326.9031,
                                -1674.377097
                            ],
                            [
                                478459.78629,
                                3670327.0828,
                                -1717.551086
                            ],
                            [
                                478459.08336,
                                3670327.1976,
                                -1746.045493
                            ],
                            [
                                478458.47896,
                                3670327.2551,
                                -1774.542335
                            ],
                            [
                                478457.97309,
                                3670327.2555,
                                -1803.041157
                            ],
                            [
                                478457.2985,
                                3670327.2207,
                                -1846.670922
                            ],
                            [
                                478456.67277,
                                3670327.2028,
                                -1890.301425
                            ],
                            [
                                478456.30439,
                                3670327.1985,
                                -1919.1624
                            ],
                            [
                                478455.99477,
                                3670327.1983,
                                -1948.024067
                            ],
                            [
                                478455.7439,
                                3670327.2019,
                                -1976.886303
                            ],
                            [
                                478455.4485,
                                3670327.2228,
                                -2020.080282
                            ],
                            [
                                478455.22525,
                                3670327.2684,
                                -2063.274675
                            ],
                            [
                                478455.02693,
                                3670327.3205,
                                -2106.509188
                            ],
                            [
                                478454.80665,
                                3670327.3609,
                                -2149.743606
                            ],
                            [
                                478454.5875,
                                3670327.3674,
                                -2193.118048
                            ],
                            [
                                478454.39407,
                                3670327.3175,
                                -2236.492584
                            ],
                            [
                                478454.21488,
                                3670327.2379,
                                -2279.722139
                            ],
                            [
                                478454.03726,
                                3670327.1549,
                                -2322.951694
                            ],
                            [
                                478453.93475,
                                3670327.0623,
                                -2351.218014
                            ],
                            [
                                478453.85849,
                                3670326.8952,
                                -2379.484074
                            ],
                            [
                                478453.80848,
                                3670326.6538,
                                -2407.749656
                            ],
                            [
                                478453.79938,
                                3670326.5248,
                                -2421.634052
                            ],
                            [
                                478453.8083,
                                3670326.4118,
                                -2435.518587
                            ],
                            [
                                478453.82562,
                                3670326.2794,
                                -2450.047967
                            ],
                            [
                                478453.84003,
                                3670326.102,
                                -2464.57687
                            ],
                            [
                                478453.85272,
                                3670325.9011,
                                -2479.185482
                            ],
                            [
                                478453.86472,
                                3670325.7001,
                                -2493.794093
                            ],
                            [
                                478453.89978,
                                3670325.5279,
                                -2508.153003
                            ],
                            [
                                478453.98204,
                                3670325.4067,
                                -2522.512241
                            ],
                            [
                                478454.09955,
                                3670325.3049,
                                -2538.086465
                            ],
                            [
                                478454.22247,
                                3670325.2075,
                                -2553.660674
                            ],
                            [
                                478454.31472,
                                3670325.1197,
                                -2567.715091
                            ],
                            [
                                478454.36476,
                                3670325.0279,
                                -2581.769697
                            ],
                            [
                                478454.38844,
                                3670324.9382,
                                -2595.534384
                            ],
                            [
                                478454.40279,
                                3670324.8526,
                                -2609.29911
                            ],
                            [
                                478454.41253,
                                3670324.7675,
                                -2623.748855
                            ],
                            [
                                478454.42139,
                                3670324.6873,
                                -2638.19863
                            ],
                            [
                                478454.41983,
                                3670324.6208,
                                -2652.663474
                            ],
                            [
                                478454.39827,
                                3670324.5769,
                                -2667.128389
                            ],
                            [
                                478454.39877,
                                3670324.5595,
                                -2681.653364
                            ],
                            [
                                478454.46365,
                                3670324.5732,
                                -2696.178198
                            ],
                            [
                                478454.57154,
                                3670324.5883,
                                -2711.502807
                            ],
                            [
                                478454.69034,
                                3670324.5719,
                                -2726.827335
                            ],
                            [
                                478454.7745,
                                3670324.5536,
                                -2741.117061
                            ],
                            [
                                478454.79527,
                                3670324.5587,
                                -2755.407032
                            ],
                            [
                                478454.80164,
                                3670324.5504,
                                -2764.62035
                            ],
                            [
                                478454.83486,
                                3670324.5039,
                                -2773.833496
                            ],
                            [
                                478454.89492,
                                3670324.4194,
                                -2783.046236
                            ],
                            [
                                478454.99277,
                                3670324.2581,
                                -2792.797689
                            ],
                            [
                                478455.13073,
                                3670323.9932,
                                -2802.546394
                            ],
                            [
                                478455.30877,
                                3670323.6249,
                                -2812.291085
                            ],
                            [
                                478455.49281,
                                3670323.2311,
                                -2819.750782
                            ],
                            [
                                478455.74134,
                                3670322.6934,
                                -2827.199607
                            ],
                            [
                                478456.05426,
                                3670322.012,
                                -2834.634224
                            ],
                            [
                                478456.43142,
                                3670321.1873,
                                -2842.051304
                            ],
                            [
                                478456.9832,
                                3670320.0391,
                                -2851.037941
                            ],
                            [
                                478457.64427,
                                3670318.7724,
                                -2860.001219
                            ],
                            [
                                478458.41441,
                                3670317.3874,
                                -2868.938247
                            ],
                            [
                                478459.37309,
                                3670315.7556,
                                -2878.730137
                            ],
                            [
                                478460.43687,
                                3670314.0336,
                                -2888.495661
                            ],
                            [
                                478461.60555,
                                3670312.2217,
                                -2898.232866
                            ],
                            [
                                478463.3512,
                                3670309.614,
                                -2911.89174
                            ],
                            [
                                478465.15637,
                                3670307.0094,
                                -2925.543455
                            ],
                            [
                                478467.12529,
                                3670304.2537,
                                -2939.863061
                            ],
                            [
                                478469.17888,
                                3670301.453,
                                -2954.162005
                            ],
                            [
                                478470.58414,
                                3670299.5669,
                                -2963.462225
                            ],
                            [
                                478472.06695,
                                3670297.5897,
                                -2972.731426
                            ],
                            [
                                478473.62706,
                                3670295.5219,
                                -2981.968071
                            ],
                            [
                                478475.93944,
                                3670292.4435,
                                -2995.36539
                            ],
                            [
                                478478.23055,
                                3670289.3492,
                                -3008.762708
                            ],
                            [
                                478480.66633,
                                3670286.025,
                                -3023.039347
                            ],
                            [
                                478483.11173,
                                3670282.6661,
                                -3037.306232
                            ],
                            [
                                478485.40022,
                                3670279.4951,
                                -3050.592222
                            ],
                            [
                                478487.69833,
                                3670276.2753,
                                -3063.864821
                            ],
                            [
                                478490.20744,
                                3670272.7491,
                                -3078.184612
                            ],
                            [
                                478492.7598,
                                3670269.1786,
                                -3092.48576
                            ],
                            [
                                478495.29187,
                                3670265.6012,
                                -3106.678963
                            ],
                            [
                                478497.77623,
                                3670262.0042,
                                -3120.875606
                            ],
                            [
                                478500.09294,
                                3670258.5942,
                                -3134.254376
                            ],
                            [
                                478502.40532,
                                3670255.163,
                                -3147.628459
                            ],
                            [
                                478504.81822,
                                3670251.5647,
                                -3161.565084
                            ],
                            [
                                478507.24016,
                                3670247.9461,
                                -3175.494884
                            ],
                            [
                                478509.68154,
                                3670244.2559,
                                -3189.65933
                            ],
                            [
                                478512.07132,
                                3670240.5643,
                                -3203.83225
                            ],
                            [
                                478514.09943,
                                3670237.386,
                                -3216.016828
                            ],
                            [
                                478516.12009,
                                3670234.198,
                                -3228.20009
                            ],
                            [
                                478518.13107,
                                3670231.046,
                                -3240.211169
                            ],
                            [
                                478520.18545,
                                3670227.8883,
                                -3252.213402
                            ],
                            [
                                478521.82019,
                                3670225.4473,
                                -3261.565819
                            ],
                            [
                                478523.48868,
                                3670223.0504,
                                -3270.923659
                            ],
                            [
                                478525.19088,
                                3670220.6975,
                                -3280.286618
                            ],
                            [
                                478527.72536,
                                3670217.3229,
                                -3294.001445
                            ],
                            [
                                478530.29612,
                                3670214.0228,
                                -3307.727644
                            ],
                            [
                                478532.93159,
                                3670210.6881,
                                -3321.720863
                            ],
                            [
                                478535.56101,
                                3670207.3346,
                                -3335.710737
                            ],
                            [
                                478538.12916,
                                3670204.0517,
                                -3349.300427
                            ],
                            [
                                478540.72808,
                                3670200.7403,
                                -3362.877318
                            ],
                            [
                                478543.36263,
                                3670197.3805,
                                -3376.519302
                            ],
                            [
                                478546.00829,
                                3670193.9902,
                                -3390.151559
                            ],
                            [
                                478548.62526,
                                3670190.5621,
                                -3403.816589
                            ],
                            [
                                478551.16072,
                                3670187.1057,
                                -3417.489879
                            ],
                            [
                                478553.70096,
                                3670183.5434,
                                -3431.538824
                            ],
                            [
                                478556.19829,
                                3670179.9837,
                                -3445.596147
                            ],
                            [
                                478558.66294,
                                3670176.4044,
                                -3459.790248
                            ],
                            [
                                478561.06139,
                                3670172.8459,
                                -3474.000938
                            ],
                            [
                                478563.3209,
                                3670169.462,
                                -3487.672822
                            ],
                            [
                                478565.55355,
                                3670166.129,
                                -3501.361636
                            ],
                            [
                                478567.7906,
                                3670162.8057,
                                -3515.187516
                            ],
                            [
                                478570.02291,
                                3670159.5113,
                                -3529.021064
                            ],
                            [
                                478572.27068,
                                3670156.2078,
                                -3543.083979
                            ],
                            [
                                478574.48441,
                                3670152.9598,
                                -3557.165232
                            ],
                            [
                                478576.63931,
                                3670149.8186,
                                -3571.057022
                            ],
                            [
                                478578.77522,
                                3670146.741,
                                -3584.965962
                            ],
                            [
                                478580.89238,
                                3670143.6662,
                                -3599.007783
                            ],
                            [
                                478582.9541,
                                3670140.5863,
                                -3613.056748
                            ],
                            [
                                478584.8775,
                                3670137.605,
                                -3626.687202
                            ],
                            [
                                478586.70419,
                                3670134.6374,
                                -3640.333928
                            ],
                            [
                                478588.50556,
                                3670131.6347,
                                -3654.177608
                            ],
                            [
                                478590.30378,
                                3670128.6301,
                                -3668.021288
                            ],
                            [
                                478592.16769,
                                3670125.5471,
                                -3682.277797
                            ],
                            [
                                478594.05917,
                                3670122.4884,
                                -3696.535878
                            ],
                            [
                                478595.91355,
                                3670119.495,
                                -3710.518996
                            ],
                            [
                                478597.73998,
                                3670116.4902,
                                -3724.503343
                            ],
                            [
                                478599.48595,
                                3670113.5876,
                                -3737.983973
                            ],
                            [
                                478601.22963,
                                3670110.6836,
                                -3751.464603
                            ],
                            [
                                478603.05769,
                                3670107.6364,
                                -3765.63036
                            ],
                            [
                                478604.88004,
                                3670104.5987,
                                -3779.798904
                            ],
                            [
                                478606.71605,
                                3670101.5514,
                                -3794.097613
                            ],
                            [
                                478608.55274,
                                3670098.5293,
                                -3808.401586
                            ],
                            [
                                478610.34967,
                                3670095.5905,
                                -3822.47072
                            ],
                            [
                                478612.12873,
                                3670092.6912,
                                -3836.550313
                            ],
                            [
                                478613.86363,
                                3670089.8571,
                                -3850.515086
                            ],
                            [
                                478615.55981,
                                3670087.0622,
                                -3864.49252
                            ],
                            [
                                478616.86859,
                                3670084.8942,
                                -3875.540764
                            ],
                            [
                                478618.14679,
                                3670082.773,
                                -3886.601689
                            ],
                            [
                                478619.12989,
                                3670081.1401,
                                -3895.248958
                            ],
                            [
                                478620.10598,
                                3670079.5188,
                                -3903.899211
                            ],
                            [
                                478620.55415,
                                3670078.8202,
                                -3907.709773
                            ],
                            [
                                478621.04191,
                                3670078.1475,
                                -3911.520131
                            ],
                            [
                                478621.56918,
                                3670077.5008,
                                -3915.329722
                            ],
                            [
                                478622.32902,
                                3670076.6816,
                                -3920.295395
                            ],
                            [
                                478623.18057,
                                3670075.8783,
                                -3925.248764
                            ],
                            [
                                478624.34477,
                                3670074.9572,
                                -3931.312713
                            ],
                            [
                                478625.63557,
                                3670074.1455,
                                -3937.366633
                            ],
                            [
                                478627.05204,
                                3670073.4436,
                                -3943.40616
                            ],
                            [
                                478628.28448,
                                3670072.931,
                                -3948.354112
                            ],
                            [
                                478629.55363,
                                3670072.4548,
                                -3953.296424
                            ],
                            [
                                478630.78689,
                                3670072.0215,
                                -3957.982385
                            ],
                            [
                                478632.04238,
                                3670071.5913,
                                -3962.66271
                            ],
                            [
                                478633.19339,
                                3670071.2012,
                                -3966.917409
                            ],
                            [
                                478634.34234,
                                3670070.8108,
                                -3971.172638
                            ],
                            [
                                478635.65658,
                                3670070.3564,
                                -3976.053245
                            ],
                            [
                                478636.96623,
                                3670069.8889,
                                -3980.933851
                            ],
                            [
                                478639.26494,
                                3670069.0541,
                                -3989.470173
                            ],
                            [
                                478641.58592,
                                3670068.2088,
                                -3997.999413
                            ],
                            [
                                478643.03981,
                                3670067.678,
                                -4003.297808
                            ],
                            [
                                478644.50211,
                                3670067.1433,
                                -4008.593492
                            ],
                            [
                                478648.29299,
                                3670065.7226,
                                -4022.271495
                            ],
                            [
                                478652.08604,
                                3670064.2343,
                                -4035.941695
                            ],
                            [
                                478656.00652,
                                3670062.6239,
                                -4050.022138
                            ],
                            [
                                478659.94561,
                                3670060.9311,
                                -4064.087693
                            ],
                            [
                                478662.54825,
                                3670059.7685,
                                -4073.331146
                            ],
                            [
                                478665.16147,
                                3670058.5621,
                                -4082.565991
                            ],
                            [
                                478667.78522,
                                3670057.312,
                                -4091.79202
                            ],
                            [
                                478671.65393,
                                3670055.4627,
                                -4105.197383
                            ],
                            [
                                478675.60946,
                                3670053.6167,
                                -4118.577816
                            ],
                            [
                                478678.22652,
                                3670052.4118,
                                -4127.54245
                            ],
                            [
                                478680.72657,
                                3670051.2651,
                                -4136.548056
                            ],
                            [
                                478683.10908,
                                3670050.1769,
                                -4145.592727
                            ],
                            [
                                478685.45415,
                                3670049.0791,
                                -4155.040631
                            ],
                            [
                                478687.65437,
                                3670047.989,
                                -4164.524242
                            ],
                            [
                                478689.70922,
                                3670046.907,
                                -4174.041352
                            ],
                            [
                                478692.5606,
                                3670045.3353,
                                -4187.89356
                            ],
                            [
                                478695.35688,
                                3670043.7517,
                                -4201.755653
                            ],
                            [
                                478698.18402,
                                3670042.0998,
                                -4215.99369
                            ],
                            [
                                478700.98015,
                                3670040.4078,
                                -4230.233155
                            ],
                            [
                                478703.70189,
                                3670038.6761,
                                -4244.354045
                            ],
                            [
                                478706.3534,
                                3670036.8757,
                                -4258.479709
                            ],
                            [
                                478708.94302,
                                3670035.0021,
                                -4272.679094
                            ],
                            [
                                478711.45379,
                                3670033.0684,
                                -4286.884594
                            ],
                            [
                                478713.89638,
                                3670031.0983,
                                -4300.999693
                            ],
                            [
                                478716.3138,
                                3670029.0896,
                                -4315.113695
                            ],
                            [
                                478730.81253,
                                3670016.8633,
                                -4400.204065
                            ],
                            [
                                478736.63331,
                                3670011.9548,
                                -4434.365144
                            ]
                        ]
                    }
                ]
            },
            "properties": {
                "name": "EBSZ-3",
                "color": [
                    28,
                    255,
                    12,
                    255
                ],
                "md": [
                    [
                        0.0,
                        11.785,
                        23.57,
                        37.15,
                        50.73,
                        64.875,
                        79.02,
                        93.16,
                        107.3,
                        121.41,
                        135.52,
                        149.315,
                        163.11,
                        176.905,
                        190.7,
                        204.18,
                        217.66,
                        230.88,
                        244.1,
                        259.855,
                        275.61,
                        289.395,
                        303.18,
                        316.94,
                        330.7,
                        344.595,
                        358.49,
                        372.31,
                        386.13,
                        400.59,
                        415.05,
                        429.42,
                        443.79,
                        458.21,
                        472.63,
                        487.075,
                        501.52,
                        515.925,
                        530.33,
                        544.79,
                        559.25,
                        573.645,
                        588.04,
                        602.43,
                        616.82,
                        631.235,
                        645.65,
                        660.09,
                        674.53,
                        688.955,
                        703.38,
                        717.765,
                        732.15,
                        746.56,
                        760.97,
                        775.375,
                        789.78,
                        804.18,
                        818.58,
                        832.975,
                        847.37,
                        861.76,
                        876.15,
                        890.555,
                        904.96,
                        919.32,
                        933.68,
                        948.12,
                        962.56,
                        977.035,
                        991.51,
                        1005.9,
                        1020.29,
                        1034.7,
                        1049.11,
                        1063.545,
                        1077.98,
                        1092.325,
                        1106.67,
                        1121.11,
                        1135.55,
                        1149.9,
                        1164.25,
                        1178.68,
                        1193.11,
                        1207.53,
                        1221.95,
                        1236.275,
                        1250.6,
                        1265.025,
                        1279.45,
                        1293.895,
                        1308.34,
                        1322.715,
                        1337.09,
                        1351.565,
                        1366.04,
                        1380.485,
                        1394.93,
                        1409.355,
                        1423.78,
                        1438.105,
                        1452.43,
                        1466.835,
                        1481.24,
                        1488.37,
                        1495.5,
                        1524.28,
                        1553.06,
                        1581.84,
                        1625.395,
                        1668.95,
                        1712.14,
                        1755.33,
                        1783.8333333,
                        1812.3366667,
                        1840.84,
                        1884.475,
                        1928.11,
                        1956.9733333,
                        1985.8366667,
                        2014.7,
                        2057.895,
                        2101.09,
                        2144.325,
                        2187.56,
                        2230.935,
                        2274.31,
                        2317.54,
                        2360.77,
                        2389.0366667,
                        2417.3033333,
                        2445.57,
                        2459.455,
                        2473.34,
                        2487.87,
                        2502.4,
                        2517.01,
                        2531.62,
                        2545.98,
                        2560.34,
                        2575.915,
                        2591.49,
                        2605.545,
                        2619.6,
                        2633.365,
                        2647.13,
                        2661.58,
                        2676.03,
                        2690.495,
                        2704.96,
                        2719.485,
                        2734.01,
                        2749.335,
                        2764.66,
                        2778.95,
                        2793.24,
                        2802.4533333,
                        2811.6666667,
                        2820.88,
                        2830.6333333,
                        2840.3866667,
                        2850.14,
                        2857.6125,
                        2865.085,
                        2872.5575,
                        2880.03,
                        2889.1066667,
                        2898.1833333,
                        2907.26,
                        2917.2333333,
                        2927.2066667,
                        2937.18,
                        2951.195,
                        2965.21,
                        2979.925,
                        2994.64,
                        3004.2333333,
                        3013.8266667,
                        3023.42,
                        3037.36,
                        3051.3,
                        3066.16,
                        3081.02,
                        3094.87,
                        3108.72,
                        3123.68,
                        3138.64,
                        3153.495,
                        3168.35,
                        3182.35,
                        3196.35,
                        3210.945,
                        3225.54,
                        3240.38,
                        3255.22,
                        3267.975,
                        3280.73,
                        3293.31,
                        3305.89,
                        3315.6933333,
                        3325.4966667,
                        3335.3,
                        3349.65,
                        3364.0,
                        3378.625,
                        3393.25,
                        3407.465,
                        3421.68,
                        3435.975,
                        3450.27,
                        3464.6,
                        3478.93,
                        3493.645,
                        3508.36,
                        3523.205,
                        3538.05,
                        3552.315,
                        3566.58,
                        3580.975,
                        3595.37,
                        3609.99,
                        3624.61,
                        3639.015,
                        3653.42,
                        3667.95,
                        3682.48,
                        3696.565,
                        3710.65,
                        3724.93,
                        3739.21,
                        3753.915,
                        3768.62,
                        3783.04,
                        3797.46,
                        3811.36,
                        3825.26,
                        3839.865,
                        3854.47,
                        3869.205,
                        3883.94,
                        3898.425,
                        3912.91,
                        3927.265,
                        3941.62,
                        3952.955,
                        3964.29,
                        3973.145,
                        3982.0,
                        3985.9,
                        3989.8,
                        3993.7,
                        3998.79,
                        4003.88,
                        4010.1233333,
                        4016.3666667,
                        4022.61,
                        4027.735,
                        4032.86,
                        4037.725,
                        4042.59,
                        4047.015,
                        4051.44,
                        4056.515,
                        4061.59,
                        4070.47,
                        4079.35,
                        4084.87,
                        4090.39,
                        4104.655,
                        4118.92,
                        4133.625,
                        4148.33,
                        4158.0033333,
                        4167.6766667,
                        4177.35,
                        4191.425,
                        4205.5,
                        4214.9166667,
                        4224.3333333,
                        4233.75,
                        4243.5466667,
                        4253.3433333,
                        4263.14,
                        4277.37,
                        4291.6,
                        4306.21,
                        4320.82,
                        4335.305,
                        4349.79,
                        4364.345,
                        4378.9,
                        4393.36,
                        4407.82,
                        4495.0,
                        4530.0
                    ]
                ]
            }
        }
    ]
}